AUTHORS
ChangeLog
LICENSE
MANIFEST.in
README.md
setup.py
tumbledore/__init__.py
tumbledore/admin.py
tumbledore/models.py
tumbledore/urls.py
tumbledore/views.py
tumbledore.egg-info/PKG-INFO
tumbledore.egg-info/SOURCES.txt
tumbledore.egg-info/dependency_links.txt
tumbledore.egg-info/requires.txt
tumbledore.egg-info/top_level.txt
tumbledore/migrations/0001_initial.py
tumbledore/migrations/0002_auto__add_field_tumblelog_sort_posts_by__add_field_tumblelogpost_sort_.py
tumbledore/migrations/__init__.py
tumbledore/templatetags/__init__.py
tumbledore/templatetags/tumbledore.py