Metadata-Version: 1.0
Name: tumbledore
Version: 0.1.7
Summary: A simple, barebones tumblelog implementation for your django site
Home-page: https://github.com/sunlightlabs/django-tumbledore
Author: Dan Drinkard
Author-email: ddrinkard@sunlightfoundation.com
License: BSD
Platform: any
